prime_num_generator/__init__.py
prime_num_generator/prime_utils.py
prime_number_generator-0.1.0.dist-info/METADATA
prime_number_generator-0.1.0.dist-info/WHEEL
prime_number_generator-0.1.0.dist-info/top_level.txt
prime_number_generator-0.1.0.dist-info/RECORD
