Metadata-Version: 2.1
Name: prime_number_generator
Version: 0.1.0
Summary: A utility package for generating, checking, and working with prime numbers
Author: Your Name
Requires-Python: >=3.8
Provides-Extra: test
Requires-Dist: pytest; extra == "test"
